server.py
outlty_mcp-0.1.0.dist-info/METADATA
outlty_mcp-0.1.0.dist-info/WHEEL
outlty_mcp-0.1.0.dist-info/entry_points.txt
outlty_mcp-0.1.0.dist-info/top_level.txt
outlty_mcp-0.1.0.dist-info/RECORD
