Metadata-Version: 2.4
Name: outlty-mcp
Version: 0.1.0
Summary: MCP server for routes as MCP tools
Author: OutlyLabs
License: MIT
Project-URL: Homepage, https://outlylabs.com
Requires-Python: >=3.10
Requires-Dist: mcp>=1.2.0
Requires-Dist: httpx>=0.27.0
Requires-Dist: anyio>=4.0.0
